rapid_snapshot-0.4.1.dist-info/METADATA
rapid_snapshot-0.4.1.dist-info/WHEEL
rapid_snapshot/__init__.py
rapid_snapshot/rapid_snapshot.pyd
rapid_snapshot-0.4.1.dist-info/RECORD
