Metadata-Version: 2.4
Name: rapid_snapshot
Version: 0.4.1
Classifier: Programming Language :: Rust
Classifier: Programming Language :: Python :: Implementation :: CPython
Classifier: Programming Language :: Python :: Implementation :: PyPy
Requires-Dist: maturin
Summary: A Diagnostics over Internet Protocol (DoIP) snapshot tool.
Author: Samuel Preston
Requires-Python: >=3.11
